aktransmitter/__init__.py
aktransmitter/core.py
aktransmitter-0.1.2.dist-info/METADATA
aktransmitter-0.1.2.dist-info/WHEEL
aktransmitter-0.1.2.dist-info/top_level.txt
aktransmitter-0.1.2.dist-info/RECORD
