Metadata-Version: 2.4
Name: aktransmitter
Version: 0.1.2
Summary: A simple file-based data transmitter
Author: Akshay Ajit Bhawar
Requires-Python: >=3.6
Dynamic: author
Dynamic: requires-python
Dynamic: summary
